optispend/__init__.py
optispend/cli.py
optispend-0.1.0.dist-info/licenses/LICENSE
optispend-0.1.0.dist-info/METADATA
optispend-0.1.0.dist-info/WHEEL
optispend-0.1.0.dist-info/entry_points.txt
optispend-0.1.0.dist-info/top_level.txt
optispend-0.1.0.dist-info/RECORD
