Metadata-Version: 2.4
Name: optispend
Version: 0.1.0
Summary: Estimate AWS Savings Plan commitments using historical billing data
Home-page: https://github.com/Richard-Barrett/aws-savings-plan-estimator
Author: Richard Barrett
License: MIT
Classifier: Programming Language :: Python :: 3
Classifier: License :: OSI Approved :: MIT License
Classifier: Operating System :: OS Independent
Requires-Python: >=3.7
License-File: LICENSE
Requires-Dist: boto3
Requires-Dist: botocore
Requires-Dist: numpy
Dynamic: license-file
